[
    {
        "key": "dbln",
        "value": "%7B%22100039840451887%22%3A%22oSW9R3at%22%7D",
        "domain": "facebook.com",
        "path": "/login/device-based/",
        "hostOnly": false,
        "creation": "2024-12-28T03:51:24.616Z",
        "lastAccessed": "2024-12-28T03:51:24.616Z"
    },
    {
        "key": "datr",
        "value": "5ORNZ1LjYybqhEyOrv16PLJq",
        "domain": "facebook.com",
        "path": "/",
        "hostOnly": false,
        "creation": "2024-12-28T03:51:24.616Z",
        "lastAccessed": "2024-12-28T03:51:24.616Z"
    },
    {
        "key": "sb",
        "value": "5ORNZ_E_hTxk1QqBQ2_qHWfk",
        "domain": "facebook.com",
        "path": "/",
        "hostOnly": false,
        "creation": "2024-12-28T03:51:24.616Z",
        "lastAccessed": "2024-12-28T03:51:24.616Z"
    },
    {
        "key": "ps_l",
        "value": "1",
        "domain": "facebook.com",
        "path": "/",
        "hostOnly": false,
        "creation": "2024-12-28T03:51:24.616Z",
        "lastAccessed": "2024-12-28T03:51:24.616Z"
    },
    {
        "key": "ps_n",
        "value": "1",
        "domain": "facebook.com",
        "path": "/",
        "hostOnly": false,
        "creation": "2024-12-28T03:51:24.616Z",
        "lastAccessed": "2024-12-28T03:51:24.616Z"
    },
    {
        "key": "vpd",
        "value": "v1%3B677x360x1.6187498569488525",
        "domain": "facebook.com",
        "path": "/",
        "hostOnly": false,
        "creation": "2024-12-28T03:51:24.616Z",
        "lastAccessed": "2024-12-28T03:51:24.616Z"
    },
    {
        "key": "locale",
        "value": "hi_IN",
        "domain": "facebook.com",
        "path": "/",
        "hostOnly": false,
        "creation": "2024-12-28T03:51:24.616Z",
        "lastAccessed": "2024-12-28T03:51:24.616Z"
    },
    {
        "key": "m_pixel_ratio",
        "value": "1.6187498569488525",
        "domain": "facebook.com",
        "path": "/",
        "hostOnly": false,
        "creation": "2024-12-28T03:51:24.616Z",
        "lastAccessed": "2024-12-28T03:51:24.616Z"
    },
    {
        "key": "c_user",
        "value": "100039840451887",
        "domain": "facebook.com",
        "path": "/",
        "hostOnly": false,
        "creation": "2024-12-28T03:51:24.617Z",
        "lastAccessed": "2024-12-28T03:51:24.617Z"
    },
    {
        "key": "fr",
        "value": "0xBnPhjpWH82op2eG.AWWX1mv74HlIeJuADHq0W-9Z6gU.BnTeTk..AAA.0.0.Bnb3Wi.AWWmdUN5eFQ",
        "domain": "facebook.com",
        "path": "/",
        "hostOnly": false,
        "creation": "2024-12-28T03:51:24.617Z",
        "lastAccessed": "2024-12-28T03:51:24.617Z"
    },
    {
        "key": "xs",
        "value": "38%3A3Xqi_dCPYy-SmA%3A2%3A1735357858%3A-1%3A4628",
        "domain": "facebook.com",
        "path": "/",
        "hostOnly": false,
        "creation": "2024-12-28T03:51:24.617Z",
        "lastAccessed": "2024-12-28T03:51:24.617Z"
    },
    {
        "key": "wd",
        "value": "445x836",
        "domain": "facebook.com",
        "path": "/",
        "hostOnly": false,
        "creation": "2024-12-28T03:51:24.617Z",
        "lastAccessed": "2024-12-28T03:51:24.617Z"
    },
    {
        "key": "wl_cbv",
        "value": "v2%3Bclient_version%3A2701%3Btimestamp%3A1735357869",
        "domain": "facebook.com",
        "path": "/",
        "hostOnly": false,
        "creation": "2024-12-28T03:51:24.617Z",
        "lastAccessed": "2024-12-28T03:51:24.617Z"
    },
    {
        "key": "fbl_st",
        "value": "100720596%3BT%3A28922631",
        "domain": "facebook.com",
        "path": "/",
        "hostOnly": false,
        "creation": "2024-12-28T03:51:24.617Z",
        "lastAccessed": "2024-12-28T03:51:24.617Z"
    }
]